open_meteo_weather_sample_jpcity/__init__.py
open_meteo_weather_sample_jpcity/__main__.py
open_meteo_weather_sample_jpcity/open_meteo_forecast_api.py
open_meteo_weather_sample_jpcity-0.0.dev2.dist-info/LICENSE.txt
open_meteo_weather_sample_jpcity-0.0.dev2.dist-info/METADATA
open_meteo_weather_sample_jpcity-0.0.dev2.dist-info/WHEEL
open_meteo_weather_sample_jpcity-0.0.dev2.dist-info/entry_points.txt
open_meteo_weather_sample_jpcity-0.0.dev2.dist-info/top_level.txt
open_meteo_weather_sample_jpcity-0.0.dev2.dist-info/RECORD
