Metadata-Version: 2.1
Name: open-meteo-weather-sample-jpcity
Version: 0.0.dev2
Summary: sample distribution-packages by legacy-setup.py
Author: Hoshimado
License-File: LICENSE.txt
Requires-Dist: certifi ==2023.7.22
Requires-Dist: charset-normalizer ==3.2.0
Requires-Dist: idna ==3.4
Requires-Dist: requests ==2.31.0
Requires-Dist: urllib3 ==2.0.4
